tsBNgen/__init__.py
tsBNgen/tsBNgen.py
tsBNgen-1.0.0.dist-info/License.txt
tsBNgen-1.0.0.dist-info/METADATA
tsBNgen-1.0.0.dist-info/WHEEL
tsBNgen-1.0.0.dist-info/top_level.txt
tsBNgen-1.0.0.dist-info/RECORD
