Metadata-Version: 2.1
Name: tsBNgen
Version: 1.0.0
Summary: Generate time series data from an arbitrary Bayesian network
Home-page: https://github.com/manitadayon/tsBNgen
Author: Manie Tadayon
Author-email: manitadayon@ucla.edu
License: MIT
Platform: UNKNOWN
Classifier: Programming Language :: Python :: 3
Classifier: License :: OSI Approved :: MIT License
Classifier: Operating System :: OS Independent
